[
    {
        "id": "1",
        "title": "Ether",
        "cover": "/portfolio/Assets/Images/Games/Ether/Ether_2.webp",
        "description": "Thumbnail ether project",
        "link": "/portfolio/games/EtherProject"
    },
    {
        "id": "2",
        "title": "Color Damage",
        "cover": "/portfolio/Assets/Images/Games/ColorDamage/colorDamage_thumb.webp",
        "description": "Thumbnail Color Damage project",
        "link": "/portfolio/games/ColorDamageProject"
    },
    {
        "id": "3",
        "title": "Rise From Hell",
        "cover": "/portfolio/Assets/Images/Games/RiseFromHell/riseFromHell_thumb.webp",
        "description": "Thumbnail Rise From Hell project",
        "link": "/portfolio/games/RiseFromHellProject"
    },
    {
        "id": "4",
        "title": "Ether Genesis",
        "cover": "/portfolio/Assets/Images/Games/EtherGenesis/etherGenesis_thumb.webp",
        "description": "Thumbnail Ether Genesis project",
        "link": "/portfolio/games/EtherGenesisProject"
    },
    {
        "id": "5",
        "title": "Apple On The Walls",
        "cover": "/portfolio/Assets/Images/Games/AOTW/aotw_thumb.webp",
        "description": "Thumbnail Apple On The Walls Project",
        "link": "/portfolio/games/AOTWProject"
    },
    {
        "id": "6",
        "title": "Lighty",
        "cover": "/portfolio/Assets/Images/Games/Lighty/lighty_thumb.webp",
        "description": "Thumbnail Lighty Project",
        "link": "/portfolio/games/LightyProject"
    }


]